{
  "slug": "how-to-heal-a-bulging-disc-naturally",
  "url": "https://www.functionalpatternsbrisbane.com/blog-page/how-to-heal-a-bulging-disc-naturally",
  "title": "How to heal a bulging disc naturally",
  "meta_title": "How to heal a bulging disc naturally — Functional Patterns Brisbane",
  "description": "Bulged and herniated discs are not \"wear and tear.\" They are caused by incorrect rotation and loading of your spine. If you want to decompress your spine and heal your bulged disc naturally - ready this life changing article. Find out what exercises to avoid and what exercise are safe for ",
  "author": "Louis Ellery",
  "date_published": "2024-03-25",
  "date_modified": "2026-03-13",
  "hero_image": "http://static1.squarespace.com/static/5d38d40f73a6ec0001796a6d/5feac172403aca2b5951ba21/660107e5b44e441e06da5d8d/1773327256091/Screenshot+2024-03-25+at+6.26.10+pm.png?format=1500w",
  "markdown": "[0](https://www.functionalpatternsbrisbane.com/cart)\n\n# How to heal a bulging disc naturally\n\nMar 25\n\nWritten By [Keriann Zipperer](https://www.functionalpatternsbrisbane.com/blog-page?author=62031332e2488e355e81cd55)\n\n## Disc Bulge Solution: Understanding the Real Cause Behind Your Pain\n\nA long-term **disc bulge solution** requires more than pain relief — it requires correcting the dysfunctional movement patterns that caused the disc to compress in the first place. At Functional Patterns Brisbane, we frequently see people who have tried massage, stretching, traction, injections, or generic physiotherapy exercises, yet still struggle with bulged disc symptoms. This is because most mainstream treatments address the symptom (pain) rather than the mechanical forces that overloaded the disc.\n\nA disc bulge typically forms when the spine lacks rotation, the pelvis becomes misaligned, the ribcage collapses, or the core remains chronically pressurised and bloated. These compensations increase compression at the lumbar spine, especially L4–L5 and L5–S1. The real **disc bulge solution** is to remove these compressive forces by improving gait, restoring thoracic extension, activating the glutes, and teaching the spine to decompress as you move.\n\nUsing the Functional Patterns method, we analyse how your body walks, rotates, and stabilises. By addressing these deeper mechanics, the disc is no longer being squashed — allowing your body to heal naturally and sustainably, without surgery or endless temporary fixes.\n\nIf you’re looking for a personalised **disc bulge solution**, you can [**book a posture assessment**](https://www.functionalpatternsbrisbane.com/book-an-assessment) so we can analyse your gait and identify the exact movement patterns contributing to the disc compression.\n\n## Current Treatment Options For Bulged Discs\n\n![](https://images.squarespace-cdn.com/content/v1/5d38d40f73a6ec0001796a6d/d610b023-d287-4921-abf4-03e39cdaf782/IMG_8643.png)\n\nAccording to the American Association of Neurological Surgeons, these are the current options for bulged disc:\n\n- pelvic traction,\n\n- gentle massage,\n\n- ice and heat therapy,\n\n- ultrasound,\n\n- electrical muscle stimulation\n\n- and stretching exercises.\n\n- Pain medication\n\n- muscle relaxants in conjunction with physical therapy.\n\n\nThe issue with this list is that there is not one item listed that addresses the root cause. These prescriptions aim to relieve pain, but they fail to address what caused the pain in the first place.\n\nOnce you receive your bulging disc MRI, your primary goal should be to naturally heal for the long-term.\n\n## So, what causes a bulged disc?\n\n![](https://images.squarespace-cdn.com/content/v1/5d38d40f73a6ec0001796a6d/0576fa03-3d15-4f33-aa67-7583c0a00f1c/gait+analysis+2.jpg)\n\nMost medical articles claim the primary cause of bulging disks is aging or 'wear and tear.'\n\nWe see that 20-40 year olds regularly present at our chronic pain practice with bulged discs.\n\nWe believe that bulged discs are a result of poor movement patterns. We see that poor movement leads to poor posture and incorrect spinal loading. Overtime, this incorrect loading leads to excessive, chronic compression of the spine.\n\nAbout 90% of bulging discs MRIs show that bulging occurs at L4-L5 and L5-S1. This causes pain in the L5 or S1 nerve that radiates down the sciatic nerve. This is area is the main site of postural compression in the spine.\n\nAlongside poor movement patterns, most people we see are chronically bloated. This core bloating pushes the stomach out and leads to further compression of the lower spine.\n\nWhen we put these factors together, it is easy to see why disc bulging is so prevent.\n\n## What Does a 'Dysfunctional Movement Pattern' Mean?\n\n![](https://images.squarespace-cdn.com/content/v1/5d38d40f73a6ec0001796a6d/cc1a8f6a-5563-41b5-b7c4-4eea1d954a8e/fp+press.jpg)\n\nYour movement pattern, or biomechanics, is the way your body moves through space. When you move, your body interacts with itself, its environment and forces such as gravity.\n\nA dysfunctional movement pattern is an unconscious or conscious movement that does not align with evolutionary standards. Evolutionary standards of movement include ratios that align with our physiology.\n\nFor example, there is a way to throw a ball that is less likely to injury you than another way.\n\nMoreover, there is a way to throw a ball that creates more power than other throwing patterns.\n\nSimilarly, there is a way to walk and stand that is more efficient and less likely to cause injury.\n\nWe can identify these patterns, ratios and muscle activations in excellent movers such as Usain bolt. We can then apply these same functional movement patterns to your own body as a set of 'guidelines.'\n\nThis is how we create safe exercises for bulging discs. We identify functional ratios, compare these to your own movement patterns, and adjust accordingly over time. This is a minimally invasive method for not only reducing herniated disc pain, but naturally healing the discs.\n\nYou cannot heal a disc that is undergoing the same amount of compression that caused the herniation in the first place.\n\nDecompressing the spine should be the main goal of any exercises for bulging discs in the lower back.\n\n## l4 l5-s1 bulging disc exercises to avoid\n\nNow that we know what causes a bulging disc, we can decide exercises to avoid.\n\nWe now know that disc bulging occurs because of excessive compression on the spine.\n\nThis instantly rules out any exercises that increase spinal compression. Below is a basic list of the most compressive, common exercises:\n\n![](https://images.squarespace-cdn.com/content/v1/5d38d40f73a6ec0001796a6d/4a9eb277-af35-483f-b2c3-a28765747e81/9AB2CB22-DB17-4205-B5F0-BC4F72876430_1_201_a.jpeg)\n\n**Squats**: Squats directly place force on the vertebrae as you move through the squatting motion.\n\n**Deadlifts:** Deadlifts put a significant load on the lower back. They compress the spinal discs as you pull and then stabilise the weight in the upright position.\n\n**Overhead Presses:** Pushing weight overhead compresses the upper spine and lumber. The vertebrae have to support not just the weight of the bar but also counteract the force of pushing up.\n\n**Leg Press:** The seated position of a leg press increases the pressure on your spine. The spine takes the load of the weight as you extend through this range of motion.\n\n**Bent Over Rows:** This exercise involves bending at the waist and lifting a weight. This puts additional pressure on the lower back as it works to stabilise the spine during the lift.\n\n**Box Jumps:** High-impact exercises like box jumps can cause compression of the spine upon landing. The force of the impact when your feet hit the ground travels up through the legs and spine. F45 and HIIT classes in general are dangerous to a fragile or damaged spine.\n\nThis rules out almost all conventional training. This is unsurprising as many people with bulged discs achieve them by training these exercises. Many people experience symptoms of bulging disc in neck c5-c6 and lower back in the gym, but ignore the signs. Their disc problems then prevent them from exercising as they cannot handle any pressure on the spinal column.\n\n## **How to heal a bulging disc naturally**\n\n![safe exercises for bulged disc](https://images.squarespace-cdn.com/content/v1/5d38d40f73a6ec0001796a6d/1698790230487-7EK1MDUBEVMDQZOBE3KA/safe+exercises+for+bulged+disc)\n\nWhether you have a broad based disc bulge, disc bulging c5 c6 or just herniated disc symptoms - this method will work for you.\n\nIf reducing pain is your goal, you need to begin decompressing your spine. This means, you need to stop doing compressive activities and start strengthening your weakened muscles.\n\nThis is where gait cycle comes into play. As we mentioned earlier - there is a correct way to move and an incorrect way to move.\n\nIf you are suffering from bulging or herniated discs, chances are you have some dysfunctional movement patterns.\n\nGait cycle is defined as the way you walk or run.\n\nSpinal decompression during gait involves the activation of muscles and structures that work together to support the spine.\n\n### Here are the key muscle groups and structures involved in supporting spinal decompression during gait:\n\n**Erector Spinae (erectors):**\n\nThis group of muscles runs along the length of the spine and works to maintain an upright posture. During gait, they contract and relax in a coordinated manner to control the movement of the spine. They help absorb the impact that walking can have on the spinal column.\n\n**Core Muscles (including the Transversus Abdominis, Multifidus, Obliques, and Rectus Abdominis):**\n\nThe core muscles help maintain proper alignment and distribute the forces exerted on the spine during movement. This aids in spinal decompression.\n\n**Gluteal Muscles (Gluteus Maximus, Medius, and Minimus):**\n\nThese muscles are essential for hip movement and stability. They help control the pelvis during gait. This then supports the alignment and decompression of the lower spine (lumbar region).\n\n**Hamstrings and Quadriceps:**\n\nThe hamstrings and quadriceps balance the forces on the knee during walking. This helps distribute the impact of each step, reducing strain on the spine. By ensuring smooth knee movement, they prevent jarring motions that can lead to spinal stress and discomfort.\n\n**Iliopsoas:**\n\nThis deep-seated muscle connects the lower spine to the femur and aids in hip flexion. It plays a role in maintaining the anterior pelvic tilt. This is crucial for the natural curvature of the lumbar spine, supporting its decompression.\n\n**Interspinalis and Intertransversarii:**\n\nThese smaller muscles between the vertebrae assist in the stabilisation and slight movements of adjacent vertebrae. They contribute to the flexibility and resilience of the spine during walking.\n\n**Latissimus Dorsi (lats):**\n\nThe latissimus dorsi has attachments to the thoracic and lumbar spine. It assists in the stabilisation and movement control of these areas during gait.\n\nThe coordination of these muscles helps minimise the impact on the spinal discs and vertebrae. It promotes spinal health and prevents injury. Proper function of these muscles, along with good posture and walking mechanics, is crucial for spinal decompression during gait.\n\n## Full Disc Herniation Recovery Using Functional Patterns\n\nLachlan first came to [F](https://www.instagram.com/fp_brisbane/?hl=en) unctional Patterns after suffering years of severe lower back pain. He had chronic sciatica down the left leg following a high school rowing injury. He had a chronic l5s1 pars defect and a herniated disc.\n\nHe also had a shoulder reconstruction following a rugby related injury. After only 6 months of training he is free of pain and adding mass to a more symmetrical decompressed structure.\n\n**After:**\n\n✅ Pain free\n\n✅ Better shoulder positioning\n\n✅ Engagement of traps and lats\n\n✅ Reduced left hip hike\n\n✅ Better core engagement\n\n✅ Improved chest expansion\n\n✅ Lumbar decompression\n\n**Before:**\n\n❌Years of Severe lower back pain\n\n❌ Sciatic pain down left leg\n\n❌ Overly retracted and depressed shoulders\n\n❌ Left hip hike\n\n❌ Lumbar compression\n\n❌ Chronically Herniated Disc\n\n❌ L5S1 Pars Defect\n\n![how to heal a bulged disc naturally](https://images.squarespace-cdn.com/content/v1/5d38d40f73a6ec0001796a6d/60c7ddcd-5537-42e5-822a-b4cfdbf43540/how+to+heal+a+bulged+disc+naturally)\n\n## Safe exercises for bulging discs:\n\nSafe exercises for bulging discs include any exercises that do not compress the spine (see the list above.)\n\nInstead, safe exercises for bulging discs decompress the spine using correct movement patterns.\n\nGait analysis can identify the movement patterns that caused the spinal compression. Functional Patterns than creates custom exercises that target the weak points in your gait cycle.\n\nThis switches on the correct muscles at the correct times to decompress the spine.\n\nThe include unilateral exercises, which means exercises that are not even on both sides. For example:\n\n- A squat is bilateral\n\n- A lunge is unilateral\n\n\nThe main factor missing from many exercises is rotation and application to gait. If you are consistently walking and moving around, why only practice exercises like squats in the gym?\n\nIt makes much more sense to train your body to move like a human than a kangaroo.\n\nHumans are bi-pedal, rotation-heavy organisms. So, if you want an exercise to decompress your spine - look into Functional Patterns Exercises.\n\nWe have helped countless people in Brisbane around the world to naturally heal their bulged dics using movement.\n\n## What is the Annulus Fibrosus?\n\nThe annulus fibrosus is the tough outer layer of a spinal disc, composed of several layers of fibrocartilage. It plays a crucial role in the structural integrity of the disc. It encases the softer, gel-like centre known as the nucleus pulposus.\n\nWhen a disc bulges, it means that the nucleus pulposus is pushing against the annulus fibrosus. This causes it to bulge outwards beyond the normal boundaries of the vertebrae.\n\nDisc bulging can occur because of the weakening of the annulus fibrosus, often caused by repetitive strain, or injury. This leads to the annulus fibrosus being unable to contain the pressure from the nucleus pulposus effectively. This bulging of the disc can press on surrounding nerves and structures, causing pain and other symptoms associated with bulged discs.\n\n[Keriann Zipperer](https://www.functionalpatternsbrisbane.com/blog-page?author=62031332e2488e355e81cd55)\n\n[Previous\\\\\n\\\\\nPrevious\\\\\n**Scoliosis Physiotherapy VS Functional Patterns**](https://www.functionalpatternsbrisbane.com/blog-page/scoliosis-physiotherapy-vs-functional-patterns) [Next\\\\\n\\\\\nNext\\\\\n\\\\\n**Transform Your Posture, Transform Your Life: A Guide to Conquering Back Pain in Brisbane**](https://www.functionalpatternsbrisbane.com/blog-page/transform-your-posture-transform-your-life-a-guide-to-conquering-back-pain-in-brisbane)\n\n* * *\n\n**Functional Patterns Brisbane**\n\n**Address:** 45 Michael Street Bulimba, QLD, 4171   Australia\n\n**Phone:** 0433801181\n\n**Email:** brisbane@functionalpatterns.com\n\n**Hours**\n\nMon 6am - 7pm\n\nTue 6am - 7pm\n\nWed 6am - 7pm\n\nThu 6am - 7pm\n\nFri 6am - 7pm\n\nSat 6am - 3pm\n\n[Privacy Policy](https://www.functionalpatternsbrisbane.com/privacy-policy)\n\n[Book An Assessment](https://impulse-rehab-centre.au1.cliniko.com/bookings?business_id=73368)\n\n[Book An Assessment](https://impulse-rehab-centre.au1.cliniko.com/bookings?business_id=73368)\n\nForm\n\n**Speak to a Human Biomechanics Specialist**\n\nWant to learn more about what we do? Want to discuss your specific circumstances to see if we are a good fit? Fill in this form!\n\nEmail\\*\n\n1/2\n\nNext\n\n1/2\n\nPreviousSubmit\n\n[![](https://images.squarespace-cdn.com/content/v1/5d38d40f73a6ec0001796a6d/822e8f9e-4839-43a1-8625-4813c68e406e/The%2BBest%2BBrisbane_W-01-removebg-preview.png)](https://www.thebestbrisbane.com/)\n\n[![](https://images.squarespace-cdn.com/content/v1/5d38d40f73a6ec0001796a6d/eaa7714a-633e-4f9d-a032-fd849123acda/Untitled%2Bdesign%2B29-removebg-preview.png)](https://www.thebestbrisbane.com/)\n\nOur Results\n\n[Chronic Pain](https://www.functionalpatternsbrisbane.com/back-pain-brisbane)\n\n[Poor Posture](https://www.functionalpatternsbrisbane.com/correct-posture)\n\n[Scoliosis & Kyphosis](https://www.functionalpatternsbrisbane.com/scoliosisresults)\n\nAbout Us\n\n[In-Person Training](https://www.functionalpatternsbrisbane.com/training-with-us)\n\n[Our Services](https://www.functionalpatternsbrisbane.com/functionalpatternsservices)\n\n[Our Facility](https://www.functionalpatternsbrisbane.com/our-facility)\n\nAbout FP\n\n[FP Assessment](https://www.functionalpatternsbrisbane.com/our-gait-based-assessment)\n\n[What Is FP?](https://www.functionalpatternsbrisbane.com/functionalpatternsmethod)\n\n[Credibility & Research](https://www.functionalpatternsbrisbane.com/functionalpatternsmethod)\n\n* * *\n\n© 2026 Functional Patterns Brisbane. All rights reserved.\n\n[Privacy Policy](https://www.functionalpatternsbrisbane.com/privacy-policy)\n\n­\n\n­"
}